LICENSE
MANIFEST.in
README.rst
setup.cfg
setup.py
pesky/__init__.py
pesky/settings/__init__.py
pesky/settings/action.py
pesky/settings/args.py
pesky/settings/errors.py
pesky/settings/namespace.py
pesky/settings/option.py
pesky/settings/parser.py
pesky/settings/section.py
pesky/settings/settings.py
pesky/settings/unittest.py
pesky/settings/version.py
pesky_settings.egg-info/PKG-INFO
pesky_settings.egg-info/SOURCES.txt
pesky_settings.egg-info/dependency_links.txt
pesky_settings.egg-info/namespace_packages.txt
pesky_settings.egg-info/top_level.txt