Metadata-Version: 1.0
Name: pesky-settings
Version: 0.0.4
Summary: Pesky settings handling routines
Home-page: https://github.com/msfrank/pesky-settings
Author: Michael Frank
Author-email: msfrank@syntaxockey.com
License: UNKNOWN
Platform: UNKNOWN
Classifier: Development Status :: 3 - Alpha
Classifier: Intended Audience :: Developers
Classifier: License :: OSI Approved :: BSD License
Classifier: Natural Language :: English
Classifier: Programming Language :: Python :: 2
